healpix_painter/__init__.py
healpix_painter/__main__.py
healpix_painter/basicpainter.py
healpix_painter/cli.py
healpix_painter/footprints.py
healpix_painter/healpix.py
healpix_painter/plotting.py
healpix_painter/py.typed
healpix_painter/data/footprints/decam.crtf
healpix_painter/data/footprints/decam_convexhull.crtf
healpix_painter/io/__init__.py
healpix_painter/io/output.py
healpix_painter/io/parser.py
healpix_painter/tilings/clustering.py
healpix_painter/tilings/decam.py
healpix_painter-0.2.0.dist-info/METADATA
healpix_painter-0.2.0.dist-info/WHEEL
healpix_painter-0.2.0.dist-info/entry_points.txt
healpix_painter-0.2.0.dist-info/licenses/LICENSE
healpix_painter-0.2.0.dist-info/RECORD
