Metadata-Version: 2.4
Name: healpix-painter
Version: 0.2.0
Summary: Add your description here
Project-URL: Source Code, https://github.com/tomas-cabrera/healpix-painter
Author-email: tomas-cabrera <tcabrera@andrew.cmu.edu>
License-File: LICENSE
Requires-Python: >=3.12
Requires-Dist: jax>=0.8.0
Requires-Dist: ligo-skymap>=2.2.2
Requires-Dist: lxml>=6.0.2
Requires-Dist: pandas>=2.3.0
Requires-Dist: parmap>=1.7.0
Requires-Dist: pytest>=8.3.5
Requires-Dist: regions>=0.10
Requires-Dist: typer>=0.16.0
